examples/__init__.py
pexelsPy/__init__.py
pexelsPy/api.py
pexelsPy/src/__init__.py
pexelsPy/src/photo.py
pexelsPy/src/video.py
pexelsPy-1.0.1.dist-info/LICENSE
pexelsPy-1.0.1.dist-info/METADATA
pexelsPy-1.0.1.dist-info/WHEEL
pexelsPy-1.0.1.dist-info/top_level.txt
pexelsPy-1.0.1.dist-info/RECORD
