Metadata-Version: 2.1
Name: pexelsPy
Version: 1.0.1
Summary: Use Pexels API v1 with Python
Home-page: https://github.com/kingsamurai123/pexels-api
Author: Sravan Kumar
Author-email: demonlyf98@protonmail.com
License: UNKNOWN
Keywords: pexels api images photos videos python
Platform: UNKNOWN
Classifier: Programming Language :: Python :: 3
Classifier: License :: OSI Approved :: MIT License
Classifier: Operating System :: OS Independent
Requires-Dist: requests
